odoo10_addon_server_environment_ir_config_parameter-10.0.1.0.1-py2.7-nspkg.pth
odoo/addons/server_environment_ir_config_parameter/README.rst
odoo/addons/server_environment_ir_config_parameter/__init__.py
odoo/addons/server_environment_ir_config_parameter/__manifest__.py
odoo/addons/server_environment_ir_config_parameter/i18n/de.po
odoo/addons/server_environment_ir_config_parameter/i18n/es.po
odoo/addons/server_environment_ir_config_parameter/i18n/nl_NL.po
odoo/addons/server_environment_ir_config_parameter/models/__init__.py
odoo/addons/server_environment_ir_config_parameter/models/ir_config_parameter.py
odoo/addons/server_environment_ir_config_parameter/tests/__init__.py
odoo/addons/server_environment_ir_config_parameter/tests/test_server_environment_ircp.py
odoo10_addon_server_environment_ir_config_parameter-10.0.1.0.1.dist-info/DESCRIPTION.rst
odoo10_addon_server_environment_ir_config_parameter-10.0.1.0.1.dist-info/METADATA
odoo10_addon_server_environment_ir_config_parameter-10.0.1.0.1.dist-info/RECORD
odoo10_addon_server_environment_ir_config_parameter-10.0.1.0.1.dist-info/WHEEL
odoo10_addon_server_environment_ir_config_parameter-10.0.1.0.1.dist-info/metadata.json
odoo10_addon_server_environment_ir_config_parameter-10.0.1.0.1.dist-info/namespace_packages.txt
odoo10_addon_server_environment_ir_config_parameter-10.0.1.0.1.dist-info/top_level.txt
