Metadata-Version: 2.0
Name: odoo10-addon-server-environment-ir-config-parameter
Version: 10.0.1.0.1
Summary: Override System Parameters from server environment file
Home-page: https://odoo-community.org/
Author: ACSONE SA/NV,Odoo Community Association (OCA)
Author-email: support@odoo-community.org
License: AGPL-3
Platform: UNKNOWN
Classifier: Programming Language :: Python :: 2.7
Classifier: Framework :: Odoo
Classifier: License :: OSI Approved :: GNU Affero General Public License v3
Requires-Dist: odoo (<10.1dev,>=10.0)
Requires-Dist: odoo10-addon-server-environment
